smithers/__init__.py
smithers/meta.py
smithers/dataset/__init__.py
smithers/dataset/abstract_dataset.py
smithers/dataset/dataset_collector.py
smithers/dataset/datasets/__init__.py
smithers/dataset/datasets/elastic_block.py
smithers/dataset/datasets/graetz.py
smithers/dataset/datasets/navier_stokes.py
smithers/dataset/datasets/termal.py
smithers/dataset/datasets/unsteady_heat.py
smithers/dataset/datasets/elastic_block/coords.npy
smithers/dataset/datasets/elastic_block/params.npy
smithers/dataset/datasets/elastic_block/snapshots.npy
smithers/dataset/datasets/elastic_block/triangles.npy
smithers/dataset/datasets/graetz/coords.npy
smithers/dataset/datasets/graetz/params.npy
smithers/dataset/datasets/graetz/points.npy
smithers/dataset/datasets/graetz/snapshots.npy
smithers/dataset/datasets/graetz/triangles.npy
smithers/dataset/datasets/navier_stokes/coords.npy
smithers/dataset/datasets/navier_stokes/params.npy
smithers/dataset/datasets/navier_stokes/snapshots.npy
smithers/dataset/datasets/navier_stokes/triangles.npy
smithers/dataset/datasets/termal/coords.npy
smithers/dataset/datasets/termal/params.npy
smithers/dataset/datasets/termal/snapshots.npy
smithers/dataset/datasets/termal/triangles.npy
smithers/dataset/datasets/unsteady_heat/coords.npy
smithers/dataset/datasets/unsteady_heat/params.npy
smithers/dataset/datasets/unsteady_heat/snapshots.npy
smithers/dataset/datasets/unsteady_heat/triangles.npy
smithers/io/__init__.py
smithers/io/basevtkhandler.py
smithers/io/openfoamhandler.py
smithers/io/stlhandler.py
smithers/io/vtkhandler.py
smithers/io/vtphandler.py
smithers/io/vtuhandler.py
smithers/io/obj/__init__.py
smithers/io/obj/objhandler.py
smithers/io/obj/objparser.py
smithers/io/openfoam/__init__.py
smithers/io/openfoam/openfoamhandler.py
smithers/io/openfoam/openfoamutils.py
smithers/plot/__init__.py
smithers/plot/complex.py
smithers/signal/__init__.py
smithers/signal/higher_order_spectrum.py
tests/__init__.py
tests/test_dataset.py
tests/test_datasets.py
smithers-0.0.1.dist-info/LICENSE.rst
smithers-0.0.1.dist-info/METADATA
smithers-0.0.1.dist-info/WHEEL
smithers-0.0.1.dist-info/top_level.txt
smithers-0.0.1.dist-info/RECORD
